pan123/__init__.py
pan123/abstracts.py
pan123/auth.py
pan123/costants.py
pan123/direct_link.py
pan123/file.py
pan123/offline_download.py
pan123/oss.py
pan123/oss_source_copy.py
pan123/share.py
pan123/transcode.py
pan123/user.py
pan123/utils/__init__.py
pan123/utils/dict_util.py
pan123/utils/exceptions.py
pan123/utils/file_metadata.py
pan123/utils/request.py
pan123-1.1.0.dist-info/licenses/LICENSE
pan123-1.1.0.dist-info/METADATA
pan123-1.1.0.dist-info/WHEEL
pan123-1.1.0.dist-info/top_level.txt
pan123-1.1.0.dist-info/RECORD
