Metadata-Version: 2.4
Name: pan123
Version: 1.1.0
Summary: 非官方的123云盘Python包
Home-page: https://github.com/SodaCodeSave/Pan123
Author: SodaCodeSave&lixuehua&Rundll86&YearnstudioYangyi&jonntd
Author-email: soda_code@outlook.com
Classifier: Programming Language :: Python :: 3
Classifier: License :: OSI Approved :: MIT License
Classifier: Operating System :: OS Independent
License-File: LICENSE
Dynamic: author
Dynamic: author-email
Dynamic: classifier
Dynamic: description
Dynamic: description-content-type
Dynamic: home-page
Dynamic: license-file
Dynamic: summary
